{
  "parent": "minecraft:recipes/root",
  "rewards": {
    "recipes": [
      "gwycraft:dyed_sticks_brown"
    ]
  },
  "criteria": {
    "has_plank": {
      "trigger": "minecraft:inventory_changed",
      "conditions": {
        "items": [
          {
            "item": "gwycraft:brown_dyed_plank"
          }
        ]
      }
    },
    "has_the_recipe": {
      "trigger": "minecraft:recipe_unlocked",
      "conditions": {
        "recipe": "gwycraft:dyed_sticks_brown"
      }
    }
  },
  "requirements": [
    [
      "has_plank",
      "has_the_recipe"
    ]
  ]
}