{
  "parent": "minecraft:recipes/root",
  "rewards": {
    "recipes": [
      "gwycraft:smelt_mud_ball_to_mud_brick_light_gray"
    ]
  },
  "criteria": {
    "has_mud_ball": {
      "trigger": "minecraft:inventory_changed",
      "conditions": {
        "items": [
          {
            "item": "gwycraft:light_gray_mud_ball"
          }
        ]
      }
    },
    "has_the_recipe": {
      "trigger": "minecraft:recipe_unlocked",
      "conditions": {
        "recipe": "gwycraft:smelt_mud_ball_to_mud_brick_light_gray"
      }
    }
  },
  "requirements": [
    [
      "has_mud_ball",
      "has_the_recipe"
    ]
  ]
}