{
  "parent": "minecraft:recipes/root",
  "rewards": {
    "recipes": [
      "gwycraft:smelt_sand_to_glass_purple"
    ]
  },
  "criteria": {
    "has_sand": {
      "trigger": "minecraft:inventory_changed",
      "conditions": {
        "items": [
          {
            "item": "gwycraft:purple_dyed_sand"
          }
        ]
      }
    },
    "has_the_recipe": {
      "trigger": "minecraft:recipe_unlocked",
      "conditions": {
        "recipe": "gwycraft:smelt_sand_to_glass_purple"
      }
    }
  },
  "requirements": [
    [
      "has_sand",
      "has_the_recipe"
    ]
  ]
}