{
  "type": "minecraft:crafting_shapeless",
  "category": "misc",
  "ingredients": [
    {
      "item": "minecraft:light_blue_dye"
    },
    {
      "item": "minecraft:water_bucket"
    },
    {
      "item": "minecraft:clay_ball"
    },
    {
      "item": "minecraft:dirt"
    },
    {
      "item": "minecraft:dirt"
    },
    {
      "item": "minecraft:dirt"
    },
    {
      "item": "minecraft:dirt"
    },
    {
      "item": "minecraft:dirt"
    },
    {
      "item": "minecraft:dirt"
    }
  ],
  "result": {
    "count": 16,
    "item": "gwycraft:light_blue_mud_ball"
  }
}