{
  "type": "minecraft:crafting_shapeless",
  "ingredients": [
    {
      "item": "minecraft:black_dye"
    },
    {
      "item": "minecraft:sandstone"
    },
    {
      "item": "minecraft:sandstone"
    },
    {
      "item": "minecraft:sandstone"
    },
    {
      "item": "minecraft:sandstone"
    },
    {
      "item": "minecraft:sandstone"
    },
    {
      "item": "minecraft:sandstone"
    },
    {
      "item": "minecraft:sandstone"
    },
    {
      "item": "minecraft:sandstone"
    }
  ],
  "result": {
    "item": "gwycraft:black_dyed_sandstone",
    "count": 8
  }
}