{
  "type": "minecraft:crafting_shapeless",
  "ingredients": [
    {
      "item": "minecraft:green_dye"
    },
    {
      "tag": "minecraft:planks"
    },
    {
      "tag": "minecraft:planks"
    },
    {
      "tag": "minecraft:planks"
    },
    {
      "tag": "minecraft:planks"
    },
    {
      "tag": "minecraft:planks"
    },
    {
      "tag": "minecraft:planks"
    },
    {
      "tag": "minecraft:planks"
    },
    {
      "tag": "minecraft:planks"
    }
  ],
  "result": {
    "item": "gwycraft:green_dyed_plank",
    "count": 8
  }
}