{
  "type": "minecraft:crafting_shapeless",
  "category": "misc",
  "ingredients": [
    {
      "item": "minecraft:purple_dye"
    },
    {
      "tag": "minecraft:leaves"
    },
    {
      "tag": "minecraft:leaves"
    },
    {
      "tag": "minecraft:leaves"
    },
    {
      "tag": "minecraft:leaves"
    },
    {
      "tag": "minecraft:leaves"
    },
    {
      "tag": "minecraft:leaves"
    },
    {
      "tag": "minecraft:leaves"
    },
    {
      "tag": "minecraft:leaves"
    }
  ],
  "result": {
    "count": 8,
    "id": "gwycraft:purple_dyed_leaf"
  }
}