{
  "type": "minecraft:crafting_shapeless",
  "category": "building",
  "ingredients": [
    {
      "item": "minecraft:glowstone"
    },
    {
      "item": "minecraft:orange_wool"
    },
    {
      "item": "minecraft:orange_wool"
    },
    {
      "item": "minecraft:orange_wool"
    },
    {
      "item": "minecraft:orange_wool"
    },
    {
      "item": "minecraft:orange_wool"
    },
    {
      "item": "minecraft:orange_wool"
    },
    {
      "item": "minecraft:orange_wool"
    },
    {
      "item": "minecraft:orange_wool"
    }
  ],
  "result": {
    "count": 8,
    "id": "gwycraft:orange_glowy_wool"
  }
}